vantutil/__init__.py
vantutil-0.0.1.dist-info/METADATA
vantutil-0.0.1.dist-info/WHEEL
vantutil-0.0.1.dist-info/top_level.txt
vantutil-0.0.1.dist-info/RECORD
