Metadata-Version: 2.4
Name: vantutil
Version: 0.0.1
Requires-Dist: build==0.10.0
Requires-Dist: twine
